{"lines": ["Let us pray together the prayer that Jesus taught his disciples.", "[long pause] [long pause]", "[long pause]", "[long pause] [long pause]", "Our Father, who art in heaven, hallowed be thy name.", "[long pause] [long pause]", "[long pause]", "[long pause] [long pause]", "Thy kingdom come, thy will be done, on earth as it is in heaven.", "[long pause] [long pause]", "[long pause]", "[long pause] [long pause]", "Give us this day our daily bread.", "[long pause] [long pause]", "[long pause]", "[long pause] [long pause]", "And forgive us our trespasses, as we forgive those who trespass against us.", "[long pause] [long pause]", "[long pause]", "[long pause] [long pause]", "And lead us not into temptation, but deliver us from evil.", "[long pause] [long pause]", "[long pause]", "[long pause] [long pause]", "Amen.", "[long pause] [long pause]"], "timestamps": [{"start": 0, "end": 3.62}, {"start": 3.62, "end": 4.98}, {"start": 4.98, "end": 6.34}, {"start": 6.34, "end": 7.7}, {"start": 7.7, "end": 12.08}, {"start": 12.08, "end": 12.08}, {"start": 12.08, "end": 12.08}, {"start": 12.08, "end": 12.08}, {"start": 12.08, "end": 18.04}, {"start": 18.04, "end": 18.04}, {"start": 18.04, "end": 18.04}, {"start": 18.04, "end": 18.04}, {"start": 18.04, "end": 18.969}, {"start": 18.969, "end": 18.969}, {"start": 18.969, "end": 18.969}, {"start": 18.969, "end": 18.969}, {"start": 18.969, "end": 24.98}, {"start": 24.98, "end": 24.98}, {"start": 24.98, "end": 24.98}, {"start": 24.98, "end": 24.98}, {"start": 24.98, "end": 30.38}, {"start": 30.38, "end": 30.747}, {"start": 30.747, "end": 31.113}, {"start": 31.113, "end": 31.48}, {"start": 31.48, "end": 31.851}, {"start": 31.851, "end": 33.489}], "duration": 33.48898}