{
  "slug": "music-cloud-drift",
  "titleEn": "Cloud Drift",
  "titleFr": "Dérive de nuages",
  "descEn": "Weightless ambient for mental release — alpha binaural drift and vagal sub-bass.",
  "descFr": "Ambiance apesanteur — dérive alpha binaurale et sub-basse vagale pour le lâcher-prise.",
  "scriptEn": "",
  "scriptFr": "",
  "category": "music",
  "durationMin": 3,
  "isSleep": false,
  "audioPathEn": "/music/vesper-ambient-09-therapeutic.mp3",
  "audioPathFr": null,
  "sortOrder": 9,
  "scienceUrl": "https://pmc.ncbi.nlm.nih.gov/articles/PMC10198548/",
  "breathing": null
}
