{
  "slug": "music-sacred-space",
  "titleEn": "Sacred Space",
  "titleFr": "Espace sacré",
  "descEn": "Contemplative ambient with alpha binaural processing and warm harmonic filtering.",
  "descFr": "Ambiance contemplative avec traitement binaural alpha et filtrage harmonique chaud.",
  "scriptEn": "",
  "scriptFr": "",
  "category": "music",
  "durationMin": 3,
  "isSleep": false,
  "audioPathEn": "/music/vesper-ambient-05-therapeutic.mp3",
  "audioPathFr": null,
  "sortOrder": 5,
  "scienceUrl": "https://pmc.ncbi.nlm.nih.gov/articles/PMC10198548/",
  "breathing": null
}
